odoo/addons/delivery_purchase/README.rst
odoo/addons/delivery_purchase/__init__.py
odoo/addons/delivery_purchase/__manifest__.py
odoo/addons/delivery_purchase/deadme/CONTRIBUTORS.rst
odoo/addons/delivery_purchase/deadme/DESCRIPTION.rst
odoo/addons/delivery_purchase/deadme/USAGE.rst
odoo/addons/delivery_purchase/i18n/delivery_purchase.pot
odoo/addons/delivery_purchase/i18n/es.po
odoo/addons/delivery_purchase/models/__init__.py
odoo/addons/delivery_purchase/models/delivery_carrier.py
odoo/addons/delivery_purchase/models/purchase_order.py
odoo/addons/delivery_purchase/models/stock_picking.py
odoo/addons/delivery_purchase/static/description/icon.png
odoo/addons/delivery_purchase/tests/__init__.py
odoo/addons/delivery_purchase/tests/test_delivery_purchase.py
odoo/addons/delivery_purchase/views/purchase_order_view.xml
odoo13_addon_delivery_purchase-13.0.1.0.1.dev3.dist-info/METADATA
odoo13_addon_delivery_purchase-13.0.1.0.1.dev3.dist-info/WHEEL
odoo13_addon_delivery_purchase-13.0.1.0.1.dev3.dist-info/top_level.txt
odoo13_addon_delivery_purchase-13.0.1.0.1.dev3.dist-info/RECORD
